{"FullPath":"F:\\infonetpos\\infonetpos-gui\\Infonet.CStoreCommander.PeripheralLayer\\bin\\x86\\Debug\\PeripheralsComponent.winmd","InProcServers":{},"Namespaces":{"PeripheralsComponent.IWindowsManager":"PeripheralsComponent","PeripheralsComponent.OPOSLineDisplayServer":"PeripheralsComponent","PeripheralsComponent.PrintUtility":"PeripheralsComponent","PeripheralsComponent.TextWeight":"PeripheralsComponent","PeripheralsComponent.IPrintUtilityClass":"PeripheralsComponent","PeripheralsComponent.IOPOSCashDrawerServer":"PeripheralsComponent","PeripheralsComponent.ILineDisplayServer":"PeripheralsComponent","PeripheralsComponent.IOPOSLineDisplayServer":"PeripheralsComponent","PeripheralsComponent.OPOSPrinterServer":"PeripheralsComponent","PeripheralsComponent.IPrinterServer":"PeripheralsComponent","PeripheralsComponent.PrinterServer":"PeripheralsComponent","PeripheralsComponent.IOPOSLineDisplayServerFactory":"PeripheralsComponent","PeripheralsComponent.SignaturePadServer":"PeripheralsComponent","PeripheralsComponent.ILineDisplayServerFactory":"PeripheralsComponent","PeripheralsComponent.IPrintUtilityFactory":"PeripheralsComponent","PeripheralsComponent.IOPOSPrinter":"PeripheralsComponent","PeripheralsComponent.IPrinterServerFactory":"PeripheralsComponent","PeripheralsComponent.LineDisplayServer":"PeripheralsComponent","PeripheralsComponent.IOPOSCashDrawerServerFactory":"PeripheralsComponent","PeripheralsComponent.TextSize":"PeripheralsComponent","PeripheralsComponent.ISignaturePadServer":"PeripheralsComponent","PeripheralsComponent.OPOSCashDrawerServer":"PeripheralsComponent","PeripheralsComponent.WindowsManager":"PeripheralsComponent","PeripheralsComponent.IOPOSPrinterServerFactory":"PeripheralsComponent","PeripheralsComponent.TextAlignment":"PeripheralsComponent"},"RootNamespace":"PeripheralsComponent","AssemblyVersion":"15.0.28307.779"}